pgpubsub/__init__.py
pgpubsub/apps.py
pgpubsub/channel.py
pgpubsub/compatibility.py
pgpubsub/listen.py
pgpubsub/listeners.py
pgpubsub/management/__init__.py
pgpubsub/management/commands/__init__.py
pgpubsub/management/commands/listen.py
pgpubsub/migrations/0001_initial.py
pgpubsub/migrations/0002_notification_created_at.py
pgpubsub/migrations/0003_notification_db_version.py
pgpubsub/migrations/0004_notification_pgpubsub_notification_set_db_version.py
pgpubsub/migrations/0005_alter_notification_options.py
pgpubsub/migrations/0006_payload_stores_proper_jsonb.py
pgpubsub/migrations/__init__.py
pgpubsub/models.py
pgpubsub/notify.py
pgpubsub/tests/__init__.py
pgpubsub/tests/apps.py
pgpubsub/tests/channels.py
pgpubsub/tests/conftest.py
pgpubsub/tests/connection.py
pgpubsub/tests/listeners.py
pgpubsub/tests/migrations/0001_initial.py
pgpubsub/tests/migrations/0002_auto_20230411_0829.py
pgpubsub/tests/migrations/0003_auto_20230516_1151.py
pgpubsub/tests/migrations/0004_alter_media_id.py
pgpubsub/tests/migrations/0005_rename_id_media_key.py
pgpubsub/tests/migrations/0006_child_parent.py
pgpubsub/tests/migrations/0007_child_pgpubsub_89ef9.py
pgpubsub/tests/migrations/0008_alter_parent_key.py
pgpubsub/tests/migrations/0009_auto_20230522_0720.py
pgpubsub/tests/migrations/0010_media_store_id.py
pgpubsub/tests/migrations/0011_payload_stores_proper_jsonb.py
pgpubsub/tests/migrations/0012_payload_context.py
pgpubsub/tests/migrations/__init__.py
pgpubsub/tests/models.py
pgpubsub/tests/test_core.py
pgpubsub/tests/test_deserialize.py
pgpubsub/tests/test_payload_context.py
pgpubsub/tests/test_trigger_deserialize.py
pgpubsub/triggers.py
django_pgpubsub-1.3.1.dist-info/LICENSE
django_pgpubsub-1.3.1.dist-info/METADATA
django_pgpubsub-1.3.1.dist-info/WHEEL
django_pgpubsub-1.3.1.dist-info/RECORD
