Metadata-Version: 2.1
Name: django-pgpubsub
Version: 1.3.1
Summary: A distributed task processing framework for Django built on top of the Postgres NOTIFY/LISTEN protocol.
Home-page: https://github.com/Opus10/django-pgpubsub
License: BSD-3-Clause
Author: Opus 10 Engineering
Requires-Python: >=3.7.0,<4
Classifier: Framework :: Django
Classifier: Intended Audience :: Developers
Classifier: License :: OSI Approved :: BSD License
Classifier: Operating System :: OS Independent
Classifier: Programming Language :: Python
Classifier: Programming Language :: Python :: 3
Classifier: Programming Language :: Python :: 3.7
Classifier: Programming Language :: Python :: 3.8
Classifier: Programming Language :: Python :: 3.9
Classifier: Programming Language :: Python :: 3.10
Classifier: Programming Language :: Python :: 3.11
Classifier: Programming Language :: Python :: 3.12
Classifier: Programming Language :: Python :: 3.13
Classifier: Programming Language :: Python :: 3 :: Only
Requires-Dist: django (>=2)
Requires-Dist: django-pgtrigger (>=4.7.0)
Project-URL: Documentation, https://django-pgpubsub.readthedocs.io
Project-URL: Repository, https://github.com/Opus10/django-pgpubsub
